{
  "date": "2026-07-17",
  "hacker_news": [
    {
      "id": 48924912,
      "title": "Inkling: Our Open-Weights Model",
      "url": "https://thinkingmachines.ai/news/introducing-inkling/",
      "score": 1126,
      "by": "vimarsh6739"
    },
    {
      "id": 48919363,
      "title": "Sleep regularity is a stronger predictor of mortality risk than sleep duration (2023)",
      "url": "https://academic.oup.com/sleep/article/47/1/zsad253/7280269",
      "score": 652,
      "by": "bilsbie"
    },
    {
      "id": 48919198,
      "title": "Prioritize mental health, and why communication is so important",
      "url": "https://ramones.dev/posts/mental-health/",
      "score": 291,
      "by": "ramon156"
    },
    {
      "id": 48915953,
      "title": "Stripe and Advent have made a joint offer to acquire PayPal – sources",
      "url": "https://www.reuters.com/business/finance/stripe-advent-offer-buy-paypal-more-than-53-billion-sources-say-2026-07-15/",
      "score": 272,
      "by": "rvz"
    },
    {
      "id": 48920475,
      "title": "Mysteries of Telegram Data Centers (2022)",
      "url": "https://dev.moe/en/3025",
      "score": 240,
      "by": "theanonymousone"
    },
    {
      "id": 48923380,
      "title": "Collection of Digital Clock Designs",
      "url": "https://clocks.dev",
      "score": 210,
      "by": "levmiseri"
    },
    {
      "id": 48922434,
      "title": "Running Gemma 4 26B at 5 tokens/sec on a 13-year-old Xeon with no GPU",
      "url": "https://www.neomindlabs.com/2026/06/08/running-gemma-4-26b-at-5-tokens-sec-on-a-13-year-old-xeon-with-no-gpu/",
      "score": 199,
      "by": "neomindryan"
    },
    {
      "id": 48919869,
      "title": "Briar is in maintenance mode",
      "url": "https://briarproject.org/news/2026-maintenance-mode/",
      "score": 167,
      "by": "ristello"
    },
    {
      "id": 48921077,
      "title": "Towards a harness that can do anything",
      "url": "https://eardatasci.github.io/c/ambiance/index.html",
      "score": 167,
      "by": "evakhoury"
    },
    {
      "id": 48921303,
      "title": "My midlife crisis Corolla is fast, furious, and modded",
      "url": "https://www.zocalopublicsquare.org/my-midlife-crisis-corolla-fast-furious-fully-modded/",
      "score": 156,
      "by": "gmays"
    },
    {
      "id": 48922838,
      "title": "Show HN: misa77 - a codec that decodes 2x faster than LZ4 (at better ratios)",
      "url": "https://github.com/welcome-to-the-sunny-side/misa77",
      "score": 128,
      "by": "nonadhocproblem"
    },
    {
      "id": 48923111,
      "title": "Open-source memory for coding agents, synced over SSH",
      "url": "https://github.com/vshulcz/deja-vu/",
      "score": 104,
      "by": "vshulcz"
    },
    {
      "id": 48881064,
      "title": "Command Line Interface Guidelines",
      "url": "https://clig.dev/",
      "score": 98,
      "by": "subset"
    },
    {
      "id": 48883578,
      "title": "Today I Rescued 7,234 Old GIFs",
      "url": "https://danq.me/2026/07/10/rescuing-7234-gifs/",
      "score": 96,
      "by": "birdculture"
    },
    {
      "id": 48926590,
      "title": "Grok Build",
      "url": "https://github.com/xai-org/grok-build",
      "score": 95,
      "by": "skp1995"
    }
  ]
}